Workbook

Sheet Shipment
A1: PRECHECK / SHIPMENT
A2: Internal reconciliation · blank template · not a customs declaration
A3: Template internal-review-v1 | Mapping internal-review-map-v1 | Policy business-v1
A5: Section | B5: Field | C5: Requirement | D5: Selected value
A6: Selected record | B6: Case reference | C6: required
A7: Selected record | B7: Case revision | C7: required
A8: Selected record | B8: Business profile version | C8: required
A9: Selected record | B9: Rule version | C9: required
A10: Selected record | B10: Procedure reference | C10: required
A11: Selected record | B11: Preparation stage | C11: required
A12: Selected record | B12: Transport mode | C12: required
A13: Selected record | B13: Containerized status | C13: required
A14: Selected record | B14: Invoice number | C14: required
A15: Selected record | B15: Invoice date | C15: required
A16: Selected record | B16: Seller name | C16: required
A17: Selected record | B17: Seller address | C17: required
... A52: Selected record | B52: Original template SHA256 | C52: required
A53: Calculation | B53: Sum of stated goods lines | C53: formula_owned | D53: =IF(COUNT(Goods!J6:J105)=0,"",SUM(Goods!J6:J105))
A54: Calculation | B54: Stated goods subtotal minus line sum | C54: formula_owned | D54: =IF(OR(D23="",D53=""),"",ROUND(D23-D53,D22))
A55: Calculation | B55: Calculated payable total | C55: formula_owned | D55: =IF(OR(D53="",D24=""),"",ROUND(D53+D24,D22))
A56: Calculation | B56: Stated minus calculated payable | C56: formula_owned | D56: =IF(OR(D25="",D55=""),"",ROUND(D25-D55,D22))

Sheet Goods
A1: PRECHECK / GOODS
A2: Internal reconciliation · blank template · not a customs declaration
A3: Template internal-review-v1 | Mapping internal-review-map-v1 | Policy business-v1
A5: Line ID | B5: Supplier item code | C5: Source goods description | D5: Country of origin | E5: Quantity | F5: Unit | G5: Unit price | H5: Price per quantity | I5: Currency | J5: Stated line amount | K5: Calculated line amount | L5: Stated minus calculated | M5: Net weight kg | N5: Gross weight kg | O5: Source reference
K6: =IF(OR(E6="",G6="",H6="",Shipment!$D$22=""),"",IF(H6<=0,"INVALID BASIS",ROUND(E6*G6/H6,Shipment!$D$22))) | L6: =IF(OR(J6="",NOT(ISNUMBER(K6))),"",ROUND(J6-K6,Shipment!$D$22))
K7: =IF(OR(E7="",G7="",H7="",Shipment!$D$22=""),"",IF(H7<=0,"INVALID BASIS",ROUND(E7*G7/H7,Shipment!$D$22))) | L7: =IF(OR(J7="",NOT(ISNUMBER(K7))),"",ROUND(J7-K7,Shipment!$D$22))
K8: =IF(OR(E8="",G8="",H8="",Shipment!$D$22=""),"",IF(H8<=0,"INVALID BASIS",ROUND(E8*G8/H8,Shipment!$D$22))) | L8: =IF(OR(J8="",NOT(ISNUMBER(K8))),"",ROUND(J8-K8,Shipment!$D$22))
K9: =IF(OR(E9="",G9="",H9="",Shipment!$D$22=""),"",IF(H9<=0,"INVALID BASIS",ROUND(E9*G9/H9,Shipment!$D$22))) | L9: =IF(OR(J9="",NOT(ISNUMBER(K9))),"",ROUND(J9-K9,Shipment!$D$22))
K10: =IF(OR(E10="",G10="",H10="",Shipment!$D$22=""),"",IF(H10<=0,"INVALID BASIS",ROUND(E10*G10/H10,Shipment!$D$22))) | L10: =IF(OR(J10="",NOT(ISNUMBER(K10))),"",ROUND(J10-K10,Shipment!$D$22))
K11: =IF(OR(E11="",G11="",H11="",Shipment!$D$22=""),"",IF(H11<=0,"INVALID BASIS",ROUND(E11*G11/H11,Shipment!$D$22))) | L11: =IF(OR(J11="",NOT(ISNUMBER(K11))),"",ROUND(J11-K11,Shipment!$D$22))
K12: =IF(OR(E12="",G12="",H12="",Shipment!$D$22=""),"",IF(H12<=0,"INVALID BASIS",ROUND(E12*G12/H12,Shipment!$D$22))) | L12: =IF(OR(J12="",NOT(ISNUMBER(K12))),"",ROUND(J12-K12,Shipment!$D$22))
K13: =IF(OR(E13="",G13="",H13="",Shipment!$D$22=""),"",IF(H13<=0,"INVALID BASIS",ROUND(E13*G13/H13,Shipment!$D$22))) | L13: =IF(OR(J13="",NOT(ISNUMBER(K13))),"",ROUND(J13-K13,Shipment!$D$22))
K14: =IF(OR(E14="",G14="",H14="",Shipment!$D$22=""),"",IF(H14<=0,"INVALID BASIS",ROUND(E14*G14/H14,Shipment!$D$22))) | L14: =IF(OR(J14="",NOT(ISNUMBER(K14))),"",ROUND(J14-K14,Shipment!$D$22))
K15: =IF(OR(E15="",G15="",H15="",Shipment!$D$22=""),"",IF(H15<=0,"INVALID BASIS",ROUND(E15*G15/H15,Shipment!$D$22))) | L15: =IF(OR(J15="",NOT(ISNUMBER(K15))),"",ROUND(J15-K15,Shipment!$D$22))
K16: =IF(OR(E16="",G16="",H16="",Shipment!$D$22=""),"",IF(H16<=0,"INVALID BASIS",ROUND(E16*G16/H16,Shipment!$D$22))) | L16: =IF(OR(J16="",NOT(ISNUMBER(K16))),"",ROUND(J16-K16,Shipment!$D$22))
K17: =IF(OR(E17="",G17="",H17="",Shipment!$D$22=""),"",IF(H17<=0,"INVALID BASIS",ROUND(E17*G17/H17,Shipment!$D$22))) | L17: =IF(OR(J17="",NOT(ISNUMBER(K17))),"",ROUND(J17-K17,Shipment!$D$22))
... K105: =IF(OR(E105="",G105="",H105="",Shipment!$D$22=""),"",IF(H105<=0,"INVALID BASIS",ROUND(E105*G105/H105,Shipment!$D$22))) | L105: =IF(OR(J105="",NOT(ISNUMBER(K105))),"",ROUND(J105-K105,Shipment!$D$22))

Sheet Containers
A1: PRECHECK / CONTAINERS
A2: Internal reconciliation · blank template · not a customs declaration
A3: Template internal-review-v1 | Mapping internal-review-map-v1 | Policy business-v1
A5: Container ID | B5: Seal ID | C5: sealed or not_sealed | D5: Transport leg | E5: Document and page | F5: Seal exception decision

Sheet Evidence
A1: PRECHECK / EVIDENCE
A2: Internal reconciliation · blank template · not a customs declaration
A3: Template internal-review-v1 | Mapping internal-review-map-v1 | Policy business-v1
A5: Selected field path | B5: Observation or reference ID | C5: Document ID | D5: Logical document type | E5: Page and source location | F5: Raw source value | G5: Normalized value | H5: Unit or currency | I5: External reference and version | J5: Verifier identity | K5: Verified at UTC

Sheet Decisions
A1: PRECHECK / DECISIONS
A2: Internal reconciliation · blank template · not a customs declaration
A3: Template internal-review-v1 | Mapping internal-review-map-v1 | Policy business-v1
A5: Decision ID | B5: Field line or leg | C5: Reason or applicability code | D5: Previous value | E5: Selected value or applicability | F5: Previous source reference | G5: Selected supporting evidence | H5: Explanation and basis | I5: Proposed by | J5: Proposed at UTC | K5: Reviewed by | L5: Reviewed at UTC | M5: Resolution
